{
  "TdTc": "0.0620000032",
  "ThTc": "0.0620000032",
  "ThTd": "0.0620000032",
  "TsTc": "0.0620000032",
  "TsTd": "0.0620000032",
  "TsTh": "0.0620000032",
  "JdJc": "0.634000029",
  "JhJc": "0.634000029",
  "JhJd": "0.634000029",
  "JsJc": "0.634000029",
  "JsJd": "0.634000029",
  "JsJh": "0.634000029",
  "QdQc": "0.62",
  "QhQc": "0.62",
  "QhQd": "0.62",
  "QsQc": "0.62",
  "QsQd": "0.62",
  "QsQh": "0.62",
  "KdKc": "1",
  "KhKc": "1",
  "KhKd": "1",
  "KsKc": "1",
  "KsKd": "1",
  "KsKh": "1",
  "AcKc": "1",
  "AcKd": "0.384",
  "AcKh": "0.384",
  "AcKs": "0.384",
  "AdKc": "0.384",
  "AdKd": "1",
  "AdKh": "0.384",
  "AdKs": "0.384",
  "AdAc": "1",
  "AhKc": "0.384",
  "AhKd": "0.384",
  "AhKh": "1",
  "AhKs": "0.384",
  "AhAc": "1",
  "AhAd": "1",
  "AsKc": "0.384",
  "AsKd": "0.384",
  "AsKh": "0.384",
  "AsKs": "1",
  "AsAc": "1",
  "AsAd": "1",
  "AsAh": "1"
}