{
  "6c4c": "0.096",
  "6d4d": "0.096",
  "6h4h": "0.096",
  "6s4s": "0.096",
  "Jc6c": "0.304",
  "Jc7c": "0.492",
  "Jc8c": "0.136",
  "Jc9c": "0.0080000004",
  "JcTd": "0.208",
  "JcTh": "0.208",
  "JcTs": "0.208",
  "Jd6d": "0.304",
  "Jd7d": "0.492",
  "Jd8d": "0.136",
  "Jd9d": "0.0080000004",
  "JdTc": "0.208",
  "JdTh": "0.208",
  "JdTs": "0.208",
  "Jh6h": "0.304",
  "Jh7h": "0.492",
  "Jh8h": "0.136",
  "Jh9h": "0.0080000004",
  "JhTc": "0.208",
  "JhTd": "0.208",
  "JhTs": "0.208",
  "Js6s": "0.304",
  "Js7s": "0.492",
  "Js8s": "0.136",
  "Js9s": "0.0080000004",
  "JsTc": "0.208",
  "JsTd": "0.208",
  "JsTh": "0.208",
  "Qc3c": "0.148",
  "Qc4c": "0.622",
  "Qc5c": "0.316",
  "Qc6c": "0.59",
  "Qc7c": "0.438",
  "Qc8c": "0.23",
  "Qc9c": "0.058",
  "QcTd": "0.09",
  "QcTh": "0.09",
  "QcTs": "0.09",
  "QcJd": "0.458",
  "QcJh": "0.458",
  "QcJs": "0.458",
  "Qd3d": "0.148",
  "Qd4d": "0.622",
  "Qd5d": "0.316",
  "Qd6d": "0.59",
  "Qd7d": "0.438",
  "Qd8d": "0.23",
  "Qd9d": "0.058",
  "QdTc": "0.09",
  "QdTh": "0.09",
  "QdTs": "0.09",
  "QdJc": "0.458",
  "QdJh": "0.458",
  "QdJs": "0.458",
  "Qh3h": "0.148",
  "Qh4h": "0.622",
  "Qh5h": "0.316",
  "Qh6h": "0.59",
  "Qh7h": "0.438",
  "Qh8h": "0.23",
  "Qh9h": "0.058",
  "QhTc": "0.09",
  "QhTd": "0.09",
  "QhTs": "0.09",
  "QhJc": "0.458",
  "QhJd": "0.458",
  "QhJs": "0.458",
  "Qs3s": "0.148",
  "Qs4s": "0.622",
  "Qs5s": "0.316",
  "Qs6s": "0.59",
  "Qs7s": "0.438",
  "Qs8s": "0.23",
  "Qs9s": "0.058",
  "QsTc": "0.09",
  "QsTd": "0.09",
  "QsTh": "0.09",
  "QsJc": "0.458",
  "QsJd": "0.458",
  "QsJh": "0.458",
  "Kc2c": "0.366",
  "Kc3c": "0.656",
  "Kc4c": "0.416000004",
  "Kc6c": "0.2779999943",
  "Kc7c": "0.092",
  "KcTd": "0.282",
  "KcTh": "0.282",
  "KcTs": "0.282",
  "KcJd": "0.496",
  "KcJh": "0.496",
  "KcJs": "0.496",
  "KcQd": "0.506",
  "KcQh": "0.506",
  "KcQs": "0.506",
  "Kd2d": "0.366",
  "Kd3d": "0.656",
  "Kd4d": "0.416000004",
  "Kd6d": "0.2779999943",
  "Kd7d": "0.092",
  "KdTc": "0.282",
  "KdTh": "0.282",
  "KdTs": "0.282",
  "KdJc": "0.496",
  "KdJh": "0.496",
  "KdJs": "0.496",
  "KdQc": "0.506",
  "KdQh": "0.506",
  "KdQs": "0.506",
  "Kh2h": "0.366",
  "Kh3h": "0.656",
  "Kh4h": "0.416000004",
  "Kh6h": "0.2779999943",
  "Kh7h": "0.092",
  "KhTc": "0.282",
  "KhTd": "0.282",
  "KhTs": "0.282",
  "KhJc": "0.496",
  "KhJd": "0.496",
  "KhJs": "0.496",
  "KhQc": "0.506",
  "KhQd": "0.506",
  "KhQs": "0.506",
  "Ks2s": "0.366",
  "Ks3s": "0.656",
  "Ks4s": "0.416000004",
  "Ks6s": "0.2779999943",
  "Ks7s": "0.092",
  "KsTc": "0.282",
  "KsTd": "0.282",
  "KsTh": "0.282",
  "KsJc": "0.496",
  "KsJd": "0.496",
  "KsJh": "0.496",
  "KsQc": "0.506",
  "KsQd": "0.506",
  "KsQh": "0.506",
  "Ac2c": "0.428",
  "Ac3c": "0.174",
  "Ac4d": "0.102",
  "Ac4h": "0.102",
  "Ac4s": "0.102",
  "Ac5d": "0.348",
  "Ac5h": "0.348",
  "Ac5s": "0.348",
  "Ac6c": "0.048",
  "Ac7d": "0.022",
  "Ac7h": "0.022",
  "Ac7s": "0.022",
  "Ac8d": "0.158",
  "Ac8h": "0.158",
  "Ac8s": "0.158",
  "Ac9d": "0.32",
  "Ac9h": "0.32",
  "Ac9s": "0.32",
  "AcTd": "0.126",
  "AcTh": "0.126",
  "AcTs": "0.126",
  "AcJd": "0.378",
  "AcJh": "0.378",
  "AcJs": "0.378",
  "AcQd": "0.222",
  "AcQh": "0.222",
  "AcQs": "0.222",
  "Ad2d": "0.428",
  "Ad3d": "0.174",
  "Ad4c": "0.102",
  "Ad4h": "0.102",
  "Ad4s": "0.102",
  "Ad5c": "0.348",
  "Ad5h": "0.348",
  "Ad5s": "0.348",
  "Ad6d": "0.048",
  "Ad7c": "0.022",
  "Ad7h": "0.022",
  "Ad7s": "0.022",
  "Ad8c": "0.158",
  "Ad8h": "0.158",
  "Ad8s": "0.158",
  "Ad9c": "0.32",
  "Ad9h": "0.32",
  "Ad9s": "0.32",
  "AdTc": "0.126",
  "AdTh": "0.126",
  "AdTs": "0.126",
  "AdJc": "0.378",
  "AdJh": "0.378",
  "AdJs": "0.378",
  "AdQc": "0.222",
  "AdQh": "0.222",
  "AdQs": "0.222",
  "Ah2h": "0.428",
  "Ah3h": "0.174",
  "Ah4c": "0.102",
  "Ah4d": "0.102",
  "Ah4s": "0.102",
  "Ah5c": "0.348",
  "Ah5d": "0.348",
  "Ah5s": "0.348",
  "Ah6h": "0.048",
  "Ah7c": "0.022",
  "Ah7d": "0.022",
  "Ah7s": "0.022",
  "Ah8c": "0.158",
  "Ah8d": "0.158",
  "Ah8s": "0.158",
  "Ah9c": "0.32",
  "Ah9d": "0.32",
  "Ah9s": "0.32",
  "AhTc": "0.126",
  "AhTd": "0.126",
  "AhTs": "0.126",
  "AhJc": "0.378",
  "AhJd": "0.378",
  "AhJs": "0.378",
  "AhQc": "0.222",
  "AhQd": "0.222",
  "AhQs": "0.222",
  "As2s": "0.428",
  "As3s": "0.174",
  "As4c": "0.102",
  "As4d": "0.102",
  "As4h": "0.102",
  "As5c": "0.348",
  "As5d": "0.348",
  "As5h": "0.348",
  "As6s": "0.048",
  "As7c": "0.022",
  "As7d": "0.022",
  "As7h": "0.022",
  "As8c": "0.158",
  "As8d": "0.158",
  "As8h": "0.158",
  "As9c": "0.32",
  "As9d": "0.32",
  "As9h": "0.32",
  "AsTc": "0.126",
  "AsTd": "0.126",
  "AsTh": "0.126",
  "AsJc": "0.378",
  "AsJd": "0.378",
  "AsJh": "0.378",
  "AsQc": "0.222",
  "AsQd": "0.222",
  "AsQh": "0.222"
}