{
  "Tc2c": "0.996",
  "Tc3c": "0.78",
  "Tc4c": "0.506",
  "Tc5c": "0.67",
  "Tc7d": "0.056",
  "Tc7h": "0.056",
  "Tc7s": "0.056",
  "Tc8d": "0.426",
  "Tc8h": "0.426",
  "Tc8s": "0.426",
  "Tc9d": "0.05",
  "Tc9h": "0.05",
  "Tc9s": "0.05",
  "Td2d": "0.996",
  "Td3d": "0.78",
  "Td4d": "0.506",
  "Td5d": "0.67",
  "Td7c": "0.056",
  "Td7h": "0.056",
  "Td7s": "0.056",
  "Td8c": "0.426",
  "Td8h": "0.426",
  "Td8s": "0.426",
  "Td9c": "0.05",
  "Td9h": "0.05",
  "Td9s": "0.05",
  "Th2h": "0.996",
  "Th3h": "0.78",
  "Th4h": "0.506",
  "Th5h": "0.67",
  "Th7c": "0.056",
  "Th7d": "0.056",
  "Th7s": "0.056",
  "Th8c": "0.426",
  "Th8d": "0.426",
  "Th8s": "0.426",
  "Th9c": "0.05",
  "Th9d": "0.05",
  "Th9s": "0.05",
  "Ts2s": "0.996",
  "Ts3s": "0.78",
  "Ts4s": "0.506",
  "Ts5s": "0.67",
  "Ts7c": "0.056",
  "Ts7d": "0.056",
  "Ts7h": "0.056",
  "Ts8c": "0.426",
  "Ts8d": "0.426",
  "Ts8h": "0.426",
  "Ts9c": "0.05",
  "Ts9d": "0.05",
  "Ts9h": "0.05",
  "Jc2c": "0.666",
  "Jc3c": "0.36",
  "Jc4c": "0.11",
  "Jc7d": "0.046",
  "Jc7h": "0.046",
  "Jc7s": "0.046",
  "Jc8d": "0.486",
  "Jc8h": "0.486",
  "Jc8s": "0.486",
  "Jc9d": "0.366",
  "Jc9h": "0.366",
  "Jc9s": "0.366",
  "Jd2d": "0.666",
  "Jd3d": "0.36",
  "Jd4d": "0.11",
  "Jd7c": "0.046",
  "Jd7h": "0.046",
  "Jd7s": "0.046",
  "Jd8c": "0.486",
  "Jd8h": "0.486",
  "Jd8s": "0.486",
  "Jd9c": "0.366",
  "Jd9h": "0.366",
  "Jd9s": "0.366",
  "Jh2h": "0.666",
  "Jh3h": "0.36",
  "Jh4h": "0.11",
  "Jh7c": "0.046",
  "Jh7d": "0.046",
  "Jh7s": "0.046",
  "Jh8c": "0.486",
  "Jh8d": "0.486",
  "Jh8s": "0.486",
  "Jh9c": "0.366",
  "Jh9d": "0.366",
  "Jh9s": "0.366",
  "Js2s": "0.666",
  "Js3s": "0.36",
  "Js4s": "0.11",
  "Js7c": "0.046",
  "Js7d": "0.046",
  "Js7h": "0.046",
  "Js8c": "0.486",
  "Js8d": "0.486",
  "Js8h": "0.486",
  "Js9c": "0.366",
  "Js9d": "0.366",
  "Js9h": "0.366",
  "Qc5d": "0.066",
  "Qc5h": "0.066",
  "Qc5s": "0.066",
  "Qc6d": "0.18",
  "Qc6h": "0.18",
  "Qc6s": "0.18",
  "Qc7d": "0.136",
  "Qc7h": "0.136",
  "Qc7s": "0.136",
  "Qc8d": "0.43",
  "Qc8h": "0.43",
  "Qc8s": "0.43",
  "Qc9d": "0.436",
  "Qc9h": "0.436",
  "Qc9s": "0.436",
  "Qd5c": "0.066",
  "Qd5h": "0.066",
  "Qd5s": "0.066",
  "Qd6c": "0.18",
  "Qd6h": "0.18",
  "Qd6s": "0.18",
  "Qd7c": "0.136",
  "Qd7h": "0.136",
  "Qd7s": "0.136",
  "Qd8c": "0.43",
  "Qd8h": "0.43",
  "Qd8s": "0.43",
  "Qd9c": "0.436",
  "Qd9h": "0.436",
  "Qd9s": "0.436",
  "Qh5c": "0.066",
  "Qh5d": "0.066",
  "Qh5s": "0.066",
  "Qh6c": "0.18",
  "Qh6d": "0.18",
  "Qh6s": "0.18",
  "Qh7c": "0.136",
  "Qh7d": "0.136",
  "Qh7s": "0.136",
  "Qh8c": "0.43",
  "Qh8d": "0.43",
  "Qh8s": "0.43",
  "Qh9c": "0.436",
  "Qh9d": "0.436",
  "Qh9s": "0.436",
  "Qs5c": "0.066",
  "Qs5d": "0.066",
  "Qs5h": "0.066",
  "Qs6c": "0.18",
  "Qs6d": "0.18",
  "Qs6h": "0.18",
  "Qs7c": "0.136",
  "Qs7d": "0.136",
  "Qs7h": "0.136",
  "Qs8c": "0.43",
  "Qs8d": "0.43",
  "Qs8h": "0.43",
  "Qs9c": "0.436",
  "Qs9d": "0.436",
  "Qs9h": "0.436",
  "Kc5d": "0.376",
  "Kc5h": "0.376",
  "Kc5s": "0.376",
  "Kc6d": "0.43",
  "Kc6h": "0.43",
  "Kc6s": "0.43",
  "Kc7d": "0.706",
  "Kc7h": "0.706",
  "Kc7s": "0.706",
  "Kc8d": "0.15",
  "Kc8h": "0.15",
  "Kc8s": "0.15",
  "Kc9d": "0.196",
  "Kc9h": "0.196",
  "Kc9s": "0.196",
  "Kd5c": "0.376",
  "Kd5h": "0.376",
  "Kd5s": "0.376",
  "Kd6c": "0.43",
  "Kd6h": "0.43",
  "Kd6s": "0.43",
  "Kd7c": "0.706",
  "Kd7h": "0.706",
  "Kd7s": "0.706",
  "Kd8c": "0.15",
  "Kd8h": "0.15",
  "Kd8s": "0.15",
  "Kd9c": "0.196",
  "Kd9h": "0.196",
  "Kd9s": "0.196",
  "Kh5c": "0.376",
  "Kh5d": "0.376",
  "Kh5s": "0.376",
  "Kh6c": "0.43",
  "Kh6d": "0.43",
  "Kh6s": "0.43",
  "Kh7c": "0.706",
  "Kh7d": "0.706",
  "Kh7s": "0.706",
  "Kh8c": "0.15",
  "Kh8d": "0.15",
  "Kh8s": "0.15",
  "Kh9c": "0.196",
  "Kh9d": "0.196",
  "Kh9s": "0.196",
  "Ks5c": "0.376",
  "Ks5d": "0.376",
  "Ks5h": "0.376",
  "Ks6c": "0.43",
  "Ks6d": "0.43",
  "Ks6h": "0.43",
  "Ks7c": "0.706",
  "Ks7d": "0.706",
  "Ks7h": "0.706",
  "Ks8c": "0.15",
  "Ks8d": "0.15",
  "Ks8h": "0.15",
  "Ks9c": "0.196",
  "Ks9d": "0.196",
  "Ks9h": "0.196",
  "Ac2d": "1",
  "Ac2h": "1",
  "Ac2s": "1",
  "Ac3d": "0.77",
  "Ac3h": "0.77",
  "Ac3s": "0.77",
  "Ac4d": "0.306",
  "Ac4h": "0.306",
  "Ac4s": "0.306",
  "Ac6d": "0.58",
  "Ac6h": "0.58",
  "Ac6s": "0.58",
  "Ac7d": "0.236",
  "Ac7h": "0.236",
  "Ac7s": "0.236",
  "Ad2c": "1",
  "Ad2h": "1",
  "Ad2s": "1",
  "Ad3c": "0.77",
  "Ad3h": "0.77",
  "Ad3s": "0.77",
  "Ad4c": "0.306",
  "Ad4h": "0.306",
  "Ad4s": "0.306",
  "Ad6c": "0.58",
  "Ad6h": "0.58",
  "Ad6s": "0.58",
  "Ad7c": "0.236",
  "Ad7h": "0.236",
  "Ad7s": "0.236",
  "Ah2c": "1",
  "Ah2d": "1",
  "Ah2s": "1",
  "Ah3c": "0.77",
  "Ah3d": "0.77",
  "Ah3s": "0.77",
  "Ah4c": "0.306",
  "Ah4d": "0.306",
  "Ah4s": "0.306",
  "Ah6c": "0.58",
  "Ah6d": "0.58",
  "Ah6s": "0.58",
  "Ah7c": "0.236",
  "Ah7d": "0.236",
  "Ah7s": "0.236",
  "As2c": "1",
  "As2d": "1",
  "As2h": "1",
  "As3c": "0.77",
  "As3d": "0.77",
  "As3h": "0.77",
  "As4c": "0.306",
  "As4d": "0.306",
  "As4h": "0.306",
  "As6c": "0.58",
  "As6d": "0.58",
  "As6h": "0.58",
  "As7c": "0.236",
  "As7d": "0.236",
  "As7h": "0.236"
}