{
  "5c4c": "0.026",
  "5d4d": "0.026",
  "5h4h": "0.026",
  "5s4s": "0.026",
  "6c5c": "0.02",
  "6d5d": "0.02",
  "6d6c": "0.004",
  "6h5h": "0.02",
  "6h6c": "0.004",
  "6h6d": "0.004",
  "6s5s": "0.02",
  "6s6c": "0.004",
  "6s6d": "0.004",
  "6s6h": "0.004",
  "7c6c": "0.022",
  "7d6d": "0.022",
  "7d7c": "0.004",
  "7h6h": "0.022",
  "7h7c": "0.004",
  "7h7d": "0.004",
  "7s6s": "0.022",
  "7s7c": "0.004",
  "7s7d": "0.004",
  "7s7h": "0.004",
  "8c6c": "0.014",
  "8c7c": "0.012",
  "8d6d": "0.014",
  "8d7d": "0.012",
  "8d8c": "0.016",
  "8h6h": "0.014",
  "8h7h": "0.012",
  "8h8c": "0.016",
  "8h8d": "0.016",
  "8s6s": "0.014",
  "8s7s": "0.012",
  "8s8c": "0.016",
  "8s8d": "0.016",
  "8s8h": "0.016",
  "9c8c": "0.026",
  "9d8d": "0.026",
  "9d9c": "0.008",
  "9h8h": "0.026",
  "9h9c": "0.008",
  "9h9d": "0.008",
  "9s8s": "0.026",
  "9s9c": "0.008",
  "9s9d": "0.008",
  "9s9h": "0.008",
  "Tc9c": "0.02",
  "Td9d": "0.02",
  "TdTc": "0.014",
  "Th9h": "0.02",
  "ThTc": "0.014",
  "ThTd": "0.014",
  "Ts9s": "0.02",
  "TsTc": "0.014",
  "TsTd": "0.014",
  "TsTh": "0.014",
  "Jc9c": "0.006",
  "JcTc": "0.012",
  "Jd9d": "0.006",
  "JdTd": "0.012",
  "Jh9h": "0.006",
  "JhTh": "0.012",
  "Js9s": "0.006",
  "JsTs": "0.012",
  "QcTc": "0.006",
  "QcJc": "0.024",
  "QdTd": "0.006",
  "QdJd": "0.024",
  "QhTh": "0.006",
  "QhJh": "0.024",
  "QsTs": "0.006",
  "QsJs": "0.024",
  "Kc6c": "0.008",
  "Kc8c": "0.002",
  "Kc9c": "0.012",
  "KcTc": "0.018",
  "KcQc": "0.02000000072",
  "KcQd": "0.01000000044",
  "KcQh": "0.01000000044",
  "KcQs": "0.01000000044",
  "Kd6d": "0.008",
  "Kd8d": "0.002",
  "Kd9d": "0.012",
  "KdTd": "0.018",
  "KdQc": "0.01000000044",
  "KdQd": "0.02000000072",
  "KdQh": "0.01000000044",
  "KdQs": "0.01000000044",
  "Kh6h": "0.008",
  "Kh8h": "0.002",
  "Kh9h": "0.012",
  "KhTh": "0.018",
  "KhQc": "0.01000000044",
  "KhQd": "0.01000000044",
  "KhQh": "0.02000000072",
  "KhQs": "0.01000000044",
  "Ks6s": "0.008",
  "Ks8s": "0.002",
  "Ks9s": "0.012",
  "KsTs": "0.018",
  "KsQc": "0.01000000044",
  "KsQd": "0.01000000044",
  "KsQh": "0.01000000044",
  "KsQs": "0.02000000072",
  "Ac3c": "0.01600000016",
  "Ac4c": "0.002000000016",
  "Ac5c": "0.01000000002",
  "Ac7c": "0.006",
  "Ac8c": "0.014",
  "Ac9c": "0.004",
  "AcTc": "0.02",
  "AcJd": "0.01400000028",
  "AcJh": "0.01400000028",
  "AcJs": "0.01400000028",
  "AcQd": "0.008",
  "AcQh": "0.008",
  "AcQs": "0.008",
  "Ad3d": "0.01600000016",
  "Ad4d": "0.002000000016",
  "Ad5d": "0.01000000002",
  "Ad7d": "0.006",
  "Ad8d": "0.014",
  "Ad9d": "0.004",
  "AdTd": "0.02",
  "AdJc": "0.01400000028",
  "AdJh": "0.01400000028",
  "AdJs": "0.01400000028",
  "AdQc": "0.008",
  "AdQh": "0.008",
  "AdQs": "0.008",
  "AdAc": "0.0180000002",
  "Ah3h": "0.01600000016",
  "Ah4h": "0.002000000016",
  "Ah5h": "0.01000000002",
  "Ah7h": "0.006",
  "Ah8h": "0.014",
  "Ah9h": "0.004",
  "AhTh": "0.02",
  "AhJc": "0.01400000028",
  "AhJd": "0.01400000028",
  "AhJs": "0.01400000028",
  "AhQc": "0.008",
  "AhQd": "0.008",
  "AhQs": "0.008",
  "AhAc": "0.0180000002",
  "AhAd": "0.0180000002",
  "As3s": "0.01600000016",
  "As4s": "0.002000000016",
  "As5s": "0.01000000002",
  "As7s": "0.006",
  "As8s": "0.014",
  "As9s": "0.004",
  "AsTs": "0.02",
  "AsJc": "0.01400000028",
  "AsJd": "0.01400000028",
  "AsJh": "0.01400000028",
  "AsQc": "0.008",
  "AsQd": "0.008",
  "AsQh": "0.008",
  "AsAc": "0.0180000002",
  "AsAd": "0.0180000002",
  "AsAh": "0.0180000002"
}